{"Nodes":[],"ExecutionTime":"2023-05-19T13:26:59.3888400Z","GenerationTime":"0001-01-01T00:00:00","PluginUserSpecFlowId":"3203a088-9a4e-4570-a816-f9cacdd9a32a","CLIUserSpecFlowId":null,"ExecutionResults":[{"ContextType":"Scenario","FeatureFolderPath":"Features","FeatureTitle":"RegistrationForm","ScenarioTitle":"Registration Form","ScenarioArguments":[],"Status":"TestError","StepResults":[{"Duration":"00:00:03.4450199","Status":"OK","Error":null,"Outputs":null},{"Duration":"00:00:00.1147944","Status":"OK","Error":null,"Outputs":null},{"Duration":"00:00:00.0663752","Status":"OK","Error":null,"Outputs":null},{"Duration":"00:00:00.1157063","Status":"OK","Error":null,"Outputs":null},{"Duration":"00:00:00.1009897","Status":"OK","Error":null,"Outputs":null},{"Duration":"00:00:00.1151285","Status":"OK","Error":null,"Outputs":null},{"Duration":"00:00:00.0430864","Status":"OK","Error":null,"Outputs":null},{"Duration":"00:00:00.0439098","Status":"OK","Error":null,"Outputs":null},{"Duration":"00:00:00.0434383","Status":"OK","Error":null,"Outputs":null},{"Duration":"00:00:00.1340260","Status":"TestError","Error":"Unable to cast object of type 'OpenQA.Selenium.WebElement' to type 'OpenQA.Selenium.Support.UI.SelectElement'.","Outputs":null},{"Duration":null,"Status":"Skipped","Error":"Unable to cast object of type 'OpenQA.Selenium.WebElement' to type 'OpenQA.Selenium.Support.UI.SelectElement'.","Outputs":null},{"Duration":null,"Status":"Skipped","Error":"Unable to cast object of type 'OpenQA.Selenium.WebElement' to type 'OpenQA.Selenium.Support.UI.SelectElement'.","Outputs":null},{"Duration":null,"Status":"Skipped","Error":"Unable to cast object of type 'OpenQA.Selenium.WebElement' to type 'OpenQA.Selenium.Support.UI.SelectElement'.","Outputs":null},{"Duration":null,"Status":"Skipped","Error":"Unable to cast object of type 'OpenQA.Selenium.WebElement' to type 'OpenQA.Selenium.Support.UI.SelectElement'.","Outputs":null},{"Duration":null,"Status":"Skipped","Error":"Unable to cast object of type 'OpenQA.Selenium.WebElement' to type 'OpenQA.Selenium.Support.UI.SelectElement'.","Outputs":null},{"Duration":null,"Status":"Skipped","Error":"Unable to cast object of type 'OpenQA.Selenium.WebElement' to type 'OpenQA.Selenium.Support.UI.SelectElement'.","Outputs":null},{"Duration":null,"Status":"Skipped","Error":"Unable to cast object of type 'OpenQA.Selenium.WebElement' to type 'OpenQA.Selenium.Support.UI.SelectElement'.","Outputs":null},{"Duration":null,"Status":"Skipped","Error":"Unable to cast object of type 'OpenQA.Selenium.WebElement' to type 'OpenQA.Selenium.Support.UI.SelectElement'.","Outputs":null},{"Duration":null,"Status":"Skipped","Error":"Unable to cast object of type 'OpenQA.Selenium.WebElement' to type 'OpenQA.Selenium.Support.UI.SelectElement'.","Outputs":null}],"Outputs":null}],"StepReports":null}